sshalosh/__init__.py
sshalosh/sshalosh.py
sshalosh_borisgorelik-0.0.3.dist-info/LICENSE
sshalosh_borisgorelik-0.0.3.dist-info/METADATA
sshalosh_borisgorelik-0.0.3.dist-info/WHEEL
sshalosh_borisgorelik-0.0.3.dist-info/top_level.txt
sshalosh_borisgorelik-0.0.3.dist-info/RECORD
